LICENSE
MANIFEST.in
README.md
pyproject.toml
setup.py
tests/test_0.py
tests/test_encoding.py
tests/test_impl.py
tests/test_io.py
tiny_vectordb/__init__.py
tiny_vectordb/config.py
tiny_vectordb/diskio.py
tiny_vectordb/jit.py
tiny_vectordb/jit_utils.py
tiny_vectordb/numpy_impl.py
tiny_vectordb/vector_collection.py
tiny_vectordb/wrap.py
tiny_vectordb.egg-info/PKG-INFO
tiny_vectordb.egg-info/SOURCES.txt
tiny_vectordb.egg-info/dependency_links.txt
tiny_vectordb.egg-info/requires.txt
tiny_vectordb.egg-info/top_level.txt
tiny_vectordb/include/b64enc.h
tiny_vectordb/include/common.h
tiny_vectordb/include/searchAlgorithm.hpp
tiny_vectordb/include/vecdbImpl.h
tiny_vectordb/src/b64enc.cpp
tiny_vectordb/src/searchAlgorithm.cpp
tiny_vectordb/src/vecdbImpl.cpp