Metadata-Version: 2.1
Name: tiny-vectordb
Version: 0.1.8
Summary: A tiny jit vector database with minimal dependencies and maximum performance.
Author-email: "Li, Mengxun" <mengxunli@whu.edu.cn>
License: MIT License
Project-URL: Homepage, https://github.com/MenxLi/tiny_vectordb
Project-URL: Bug Tracker, https://github.com/MenxLi/tiny_vectordb/issues
Classifier: Development Status :: 3 - Alpha
Classifier: Intended Audience :: Developers
Classifier: Operating System :: Unix
Classifier: Topic :: Database
Classifier: Programming Language :: Python :: 3
Classifier: Programming Language :: C++
Requires-Python: >=3.8
License-File: LICENSE
